rclpy/__init__.py
rclpy/callback_groups.py
rclpy/client.py
rclpy/clock.py
rclpy/constants.py
rclpy/context.py
rclpy/duration.py
rclpy/exceptions.py
rclpy/executors.py
rclpy/expand_topic_name.py
rclpy/guard_condition.py
rclpy/logging.py
rclpy/node.py
rclpy/parameter.py
rclpy/parameter_service.py
rclpy/publisher.py
rclpy/qos.py
rclpy/qos_event.py
rclpy/qos_overriding_options.py
rclpy/serialization.py
rclpy/service.py
rclpy/signals.py
rclpy/subscription.py
rclpy/task.py
rclpy/time.py
rclpy/time_source.py
rclpy/timer.py
rclpy/topic_endpoint_info.py
rclpy/topic_or_service_is_hidden.py
rclpy/type_support.py
rclpy/utilities.py
rclpy/validate_full_topic_name.py
rclpy/validate_namespace.py
rclpy/validate_node_name.py
rclpy/validate_parameter_name.py
rclpy/validate_topic_name.py
rclpy/wait_for_message.py
rclpy/waitable.py
rclpy/action/__init__.py
rclpy/action/client.py
rclpy/action/graph.py
rclpy/action/server.py
rclpy/impl/__init__.py
rclpy/impl/implementation_singleton.py
rclpy/impl/logging_severity.py
rclpy/impl/rcutils_logger.py
rclpy/lifecycle/__init__.py
rclpy/lifecycle/managed_entity.py
rclpy/lifecycle/node.py
rclpy/lifecycle/publisher.py
rclpy_intellisense-1.2.0.dist-info/LICENSE
rclpy_intellisense-1.2.0.dist-info/METADATA
rclpy_intellisense-1.2.0.dist-info/WHEEL
rclpy_intellisense-1.2.0.dist-info/top_level.txt
rclpy_intellisense-1.2.0.dist-info/RECORD
