Metadata-Version: 2.1
Name: rclpy-intellisense
Version: 1.2.0
Summary: Get intellisense for rclpy
Author-email: offish <overutilization@gmail.com>
Project-URL: Homepage, https://github.com/offish/rclpy-intellisense
Project-URL: Bug Tracker, https://github.com/offish/rclpy-intellisense/issues
Classifier: Programming Language :: Python :: 3
Classifier: License :: OSI Approved :: MIT License
Classifier: Operating System :: OS Independent
Requires-Python: >=3.10
License-File: LICENSE
